TwitchDev/__init__.py
TwitchDev-0.0.5.dist-info/METADATA
TwitchDev-0.0.5.dist-info/WHEEL
TwitchDev-0.0.5.dist-info/top_level.txt
TwitchDev-0.0.5.dist-info/RECORD
