Metadata-Version: 2.1
Name: TwitchDev
Version: 0.0.5
Summary: TwitchDev
Home-page: https://github.com/dndbxkwh/TwitchDev
Author: dndbxkwh
Author-email: dndbxkwh@gmail.com
License: UNKNOWN
Platform: UNKNOWN
Classifier: Programming Language :: Python :: 3
Requires-Python: >=3.6
